autoslug/__init__.py
autoslug/fields.py
autoslug/models.py
autoslug/settings.py
autoslug/utils.py
django_autoslug-1.9.9.dist-info/COPYING.LESSER
django_autoslug-1.9.9.dist-info/METADATA
django_autoslug-1.9.9.dist-info/WHEEL
django_autoslug-1.9.9.dist-info/top_level.txt
django_autoslug-1.9.9.dist-info/RECORD
