Metadata-Version: 2.1
Name: django-autoslug
Version: 1.9.9
Summary: An automated slug field for Django.
Home-page: https://github.com/justinmayer/django-autoslug/
Author: Justin Mayer
Author-email: entrop@gmail.com
License: GNU Lesser General Public License (LGPL), Version 3
Download-URL: https://github.com/justinmayer/django-autoslug/archive/master.zip
Keywords: django field slug auto unique transliteration i18n
Platform: UNKNOWN
Classifier: Development Status :: 5 - Production/Stable
Classifier: Environment :: Web Environment
Classifier: Framework :: Django
Classifier: Intended Audience :: Developers
Classifier: License :: OSI Approved :: GNU Library or Lesser General Public License (LGPL)
Classifier: Framework :: Django
Classifier: Framework :: Django :: 3.2
Classifier: Programming Language :: Python
Classifier: Programming Language :: Python :: 3
Classifier: Programming Language :: Python :: 3.7
Classifier: Programming Language :: Python :: 3.8
Classifier: Programming Language :: Python :: Implementation :: CPython
Classifier: Programming Language :: Python :: Implementation :: PyPy
Classifier: Topic :: Software Development :: Libraries :: Python Modules
Classifier: Topic :: Text Processing :: General
Requires: python (>= 3.7)
Requires: django (>= 3.2)
Provides-Extra: cyrillic
Provides-Extra: translitcodec
License-File: COPYING.LESSER
